utils_qgofer/__init__.py
utils_qgofer/_modidx.py
utils_qgofer/core.py
utils_qgofer-0.0.1.dist-info/LICENSE
utils_qgofer-0.0.1.dist-info/METADATA
utils_qgofer-0.0.1.dist-info/WHEEL
utils_qgofer-0.0.1.dist-info/entry_points.txt
utils_qgofer-0.0.1.dist-info/top_level.txt
utils_qgofer-0.0.1.dist-info/RECORD
