Metadata-Version: 2.1
Name: utils-qgofer
Version: 0.0.1
Summary: Utility functions that cut across most qgofer projects
Home-page: https://github.com/qgofer/utils-qgofer
Author: acquayefrank
Author-email: acquayefrank@gmail.com
License: Apache Software License 2.0
Keywords: nbdev jupyter notebook python qgofer
Classifier: Development Status :: 4 - Beta
Classifier: Intended Audience :: Developers
Classifier: Natural Language :: English
Classifier: Programming Language :: Python :: 3.7
Classifier: Programming Language :: Python :: 3.8
Classifier: Programming Language :: Python :: 3.9
Classifier: Programming Language :: Python :: 3.10
Classifier: License :: OSI Approved :: Apache Software License
Requires-Python: >=3.7
License-File: LICENSE
Requires-Dist: orjson
Provides-Extra: dev
